[{"value":"VILLE_656618409","text":"01170 Segny"},{"value":"VILLE_797412604","text":"01190 Sermoyer"},{"value":"VILLE_78919847","text":"01420 Seyssel"},{"value":"VILLE_896993187","text":"01450 Serrieres Sur Ain"},{"value":"VILLE_898347804","text":"01470 Seillonnaz"},{"value":"VILLE_66734144","text":"01470 Serrieres De Briord"},{"value":"VILLE_673582904","text":"01560 Servignat"},{"value":"VILLE_172681390","text":"01630 Sergy"},{"value":"VILLE_725644375","text":"01960 Servas"},{"value":"VILLE_366967546","text":"02000 Verneuil Sur Serre"},{"value":"VILLE_210388079","text":"02110 Seboncourt"},{"value":"VILLE_605773658","text":"02110 Serain"},{"value":"VILLE_532783908","text":"02130 Sergy"},{"value":"VILLE_639292056","text":"02130 Seringes Et Nesles"},{"value":"VILLE_391556563","text":"02150 La Selve"},{"value":"VILLE_557035094","text":"02160 Serval"},{"value":"VILLE_987333880","text":"02200 Berzy Le Sec"},{"value":"VILLE_346050864","text":"02200 Septmonts"},{"value":"VILLE_742243907","text":"02220 Serches"},{"value":"VILLE_36040051","text":"02220 Sermoise"},{"value":"VILLE_75937260","text":"02240 Pleine Selve"},{"value":"VILLE_971779374","text":"02240 Sery Les Mezieres"},{"value":"VILLE_591420301","text":"02240 Villers Le Sec"},{"value":"VILLE_536370028","text":"02250 Bosmont Sur Serre"},{"value":"VILLE_974465288","text":"02270 Assis Sur Serre"},{"value":"VILLE_809628094","text":"02270 Barenton Sur Serre"},{"value":"VILLE_755529466","text":"02270 Crecy Sur Serre"},{"value":"VILLE_3316523","text":"02270 Pouilly Sur Serre"},{"value":"VILLE_398104122","text":"02300 Selens"},{"value":"VILLE_751092295","text":"02340 Agnicourt Et Sechelles"},{"value":"VILLE_57200708","text":"02360 Rouvroy Sur Serre"},{"value":"VILLE_333389483","text":"02360 Rozoy Sur Serre"},{"value":"VILLE_948208400","text":"02410 Septvaux"},{"value":"VILLE_381333622","text":"02420 Sequehart"},{"value":"VILLE_372461209","text":"02700 Servais"},{"value":"VILLE_548205227","text":"02760 Francilly Selency"},{"value":"VILLE_43357940","text":"02790 Seraucourt Le Grand"},{"value":"VILLE_474993625","text":"03120 Servilly"},{"value":"VILLE_132828540","text":"03140 Taxat Senat"},{"value":"VILLE_634396819","text":"03260 Seuillet"},{"value":"VILLE_539703533","text":"03700 Serbannes"},{"value":"VILLE_647646001","text":"04140 Saint Martin Les Seyne"},{"value":"VILLE_675534842","text":"04140 Selonnet"},{"value":"VILLE_356621176","text":"04140 Seyne Les Alpes"},{"value":"VILLE_589152695","text":"04330 Senez"},{"value":"VILLE_74037537","text":"05240 Serre Chevalier"},{"value":"VILLE_693937406","text":"05700 Serres"},{"value":"VILLE_997759326","text":"06660 Saint Dalmas Le Selvage"},{"value":"VILLE_999822087","text":"06750 Seranon"},{"value":"VILLE_460861499","text":"07190 Saint Etienne De Serre"},{"value":"VILLE_23849028","text":"07200 Saint Julien Du Serre"},{"value":"VILLE_41402931","text":"07200 Saint Sernin"},{"value":"VILLE_428177717","text":"07340 Serrieres"},{"value":"VILLE_112703114","text":"07610 Secheras"},{"value":"VILLE_938273229","text":"07800 Saint Cierge La Serre"},{"value":"VILLE_405353281","text":"08000 Villers Semeuse"},{"value":"VILLE_768166626","text":"08130 Semuy"},{"value":"VILLE_106963947","text":"08150 Secheval"},{"value":"VILLE_681305206","text":"08200 Sedan"},{"value":"VILLE_257452603","text":"08220 Seraincourt"},{"value":"VILLE_583321838","text":"08220 Sevigny Waleppe"},{"value":"VILLE_50447053","text":"08230 Sevigny La Foret"},{"value":"VILLE_142990278","text":"08250 Sechault"},{"value":"VILLE_275790736","text":"08250 Senuc"},{"value":"VILLE_821915285","text":"08270 Sery"},{"value":"VILLE_374341045","text":"08300 Seuil"},{"value":"VILLE_665357632","text":"08400 Semide"},{"value":"VILLE_992423097","text":"09000 Serres Sur Arget"},{"value":"VILLE_140075282","text":"09120 Segura"},{"value":"VILLE_241946218","text":"09140 Seix"},{"value":"VILLE_613310451","text":"09140 Sentenac D'oust"},{"value":"VILLE_450619911","text":"09190 Lorp Sentaraille"},{"value":"VILLE_426067099","text":"09220 Sem"},{"value":"VILLE_31273130","text":"09220 Suc Et Sentenac"},{"value":"VILLE_242838122","text":"09240 La Bastide De Serou"},{"value":"VILLE_933658689","text":"09240 Sentenac De Serou"},{"value":"VILLE_589242497","text":"09250 Senconac"},{"value":"VILLE_462112512","text":"09400 Cazenave Serres Et Allens"},{"value":"VILLE_900620033","text":"09400 Rabat Les Trois Seigneurs"},{"value":"VILLE_180646332","text":"09420 Esplas De Serou"},{"value":"VILLE_339973190","text":"09800 Sentein"},{"value":"VILLE_389373819","text":"10100 Romilly Sur Seine"},{"value":"VILLE_474770922","text":"10110 Bar Sur Seine"},{"value":"VILLE_290578379","text":"10140 Longpre Le Sec"},{"value":"VILLE_630335531","text":"10170 Mery Sur Seine"},{"value":"VILLE_791534955","text":"10180 Saint Benoit Sur Seine"},{"value":"VILLE_146287555","text":"10200 Colombe Le Sec"},{"value":"VILLE_998831437","text":"10220 Mesnil Sellieres"},{"value":"VILLE_493942662","text":"10250 Gye Sur Seine"},{"value":"VILLE_546664150","text":"10250 Mussy Sur Seine"},{"value":"VILLE_122418911","text":"10250 Neuville Sur Seine"},{"value":"VILLE_564785495","text":"10400 Marnay Sur Seine"},{"value":"VILLE_68475902","text":"10400 Nogent Sur Seine"},{"value":"VILLE_152216327","text":"10400 Pont Sur Seine"},{"value":"VILLE_980005743","text":"10510 Origny Le Sec"},{"value":"VILLE_745943886","text":"10700 Semoine"},{"value":"VILLE_689289941","text":"11190 La Serpent"},{"value":"VILLE_377397904","text":"11190 Serres"},{"value":"VILLE_384216123","text":"11220 Servies En Val"},{"value":"VILLE_339239873","text":"11240 Seignalens"},{"value":"VILLE_483704372","text":"11270 Gaja La Selve"},{"value":"VILLE_486759271","text":"11420 Saint Sernin"},{"value":"VILLE_519641776","text":"12150 Severac Le Chateau"},{"value":"VILLE_530607330","text":"12170 La Selve"},{"value":"VILLE_356084952","text":"12190 Sebrazac"},{"value":"VILLE_86724453","text":"12290 Segur"},{"value":"VILLE_748666704","text":"12310 Severac L'eglise"},{"value":"VILLE_144872551","text":"12320 Senergues"},{"value":"VILLE_57549497","text":"12370 Saint Sever Du Moustier"},{"value":"VILLE_459708795","text":"12380 La Serre"},{"value":"VILLE_969420117","text":"12380 Saint Sernin Sur Rance"},{"value":"VILLE_228189981","text":"12740 Sebazac Concoures"},{"value":"VILLE_408924474","text":"13240 Septemes Les Vallons"},{"value":"VILLE_892737842","text":"13560 Senas"},{"value":"VILLE_661300229","text":"14240 Sept Vents"},{"value":"VILLE_503881550","text":"14250 Juvigny Sur Seulles"},{"value":"VILLE_491158913","text":"14250 Saint Vaast Sur Seulles"},{"value":"VILLE_492584195","text":"14250 Tilly Sur Seulles"},{"value":"VILLE_402357101","text":"14290 Preaux Saint Sebastien"},{"value":"VILLE_206801152","text":"14310 Amaye Sur Seulles"},{"value":"VILLE_424337905","text":"14310 Saint Louet Sur Seulles"},{"value":"VILLE_363424975","text":"14380 Saint Sever Calvados"},{"value":"VILLE_311008100","text":"14380 Sept Freres"},{"value":"VILLE_543688082","text":"14400 Conde Sur Seulles"},{"value":"VILLE_364564626","text":"14400 Esquay Sur Seulles"},{"value":"VILLE_3712757","text":"14400 Vaux Sur Seulles"},{"value":"VILLE_742860739","text":"14480 Colombiers Sur Seulles"},{"value":"VILLE_239801860","text":"14480 Villiers Le Sec"},{"value":"VILLE_238846122","text":"14540 Garcelles Secqueville"},{"value":"VILLE_121653482","text":"14740 Secqueville En Bessin"},{"value":"VILLE_128241960","text":"15100 Seriers"},{"value":"VILLE_578799017","text":"15290 La Segalassiere"},{"value":"VILLE_989496412","text":"15300 Segur Les Villas"},{"value":"VILLE_948942888","text":"15340 Senezergues"},{"value":"VILLE_632099045","text":"16130 Segonzac"},{"value":"VILLE_457958417","text":"16200 Sainte Severe"},{"value":"VILLE_356914061","text":"16390 Saint Severin"},{"value":"VILLE_421429165","text":"16410 Sers"},{"value":"VILLE_361349262","text":"17113 Mornac Sur Seudre"},{"value":"VILLE_496648612","text":"17120 Chenac Saint Seurin D'uzet"},{"value":"VILLE_324827484","text":"17120 Semussac"},{"value":"VILLE_471366201","text":"17150 Semillac"},{"value":"VILLE_615460884","text":"17150 Semoussac"},{"value":"VILLE_149662686","text":"17240 Saint Germain Du Seudre"},{"value":"VILLE_978606232","text":"17330 Saint Severin Sur Boutonne"},{"value":"VILLE_10999869","text":"17510 Seigne"},{"value":"VILLE_585881598","text":"17600 Nieulle Sur Seudre"},{"value":"VILLE_15653237","text":"17770 Le Seure"},{"value":"VILLE_661807846","text":"17800 Fleac Sur Seugne"},{"value":"VILLE_161811740","text":"17800 Saint Seurin De Palenne"},{"value":"VILLE_820437390","text":"17800 Saint Sever De Saintonge"},{"value":"VILLE_219834025","text":"18140 Sevry"},{"value":"VILLE_891000332","text":"18190 Serruelles"},{"value":"VILLE_499983865","text":"18300 Sens Beaujeu"},{"value":"VILLE_62511982","text":"18340 Sennecay"},{"value":"VILLE_228736449","text":"18340 Soye En Septaine"},{"value":"VILLE_42281398","text":"18390 Savigny En Septaine"},{"value":"VILLE_256872258","text":"18800 Farges En Septaine"},{"value":"VILLE_821978622","text":"19160 Serandon"},{"value":"VILLE_64816595","text":"19190 Serilhac"},{"value":"VILLE_928197011","text":"19210 Saint Martin Sepert"},{"value":"VILLE_400456586","text":"19220 Servieres Le Chateau"},{"value":"VILLE_96244136","text":"19230 Segur Le Chateau"},{"value":"VILLE_55651343","text":"19290 Saint Setiers"},{"value":"VILLE_798210874","text":"19310 Segonzac"},{"value":"VILLE_23320685","text":"19430 Sexcles"},{"value":"VILLE_733666980","text":"19700 Seilhac"},{"value":"VILLE_765259714","text":"20127 Serra Di Scopamene"},{"value":"VILLE_909798510","text":"20140 Serra Di Ferro"},{"value":"VILLE_424387573","text":"20147 Serriera"},{"value":"VILLE_995139413","text":"20212 Sermano"},{"value":"VILLE_172061232","text":"20243 Serra Di Fiumorbo"},{"value":"VILLE_887079693","text":"21130 Saint Seine En Bache"},{"value":"VILLE_677096362","text":"21140 Courcelles Les Semur"},{"value":"VILLE_524210609","text":"21140 Massingy Les Semur"},{"value":"VILLE_166799992","text":"21140 Semur En Auxois"},{"value":"VILLE_845316946","text":"21150 Seigny"},{"value":"VILLE_100083526","text":"21220 Segrois"},{"value":"VILLE_28800229","text":"21220 Semezanges"},{"value":"VILLE_562984417","text":"21250 Montagny Les Seurre"},{"value":"VILLE_933793281","text":"21250 Seurre"},{"value":"VILLE_683157330","text":"21260 Selongey"},{"value":"VILLE_186212070","text":"21320 Semarey"},{"value":"VILLE_988491230","text":"21330 Fontaines Les Seches"},{"value":"VILLE_307631556","text":"21380 Curtil Saint Seine"},{"value":"VILLE_675680684","text":"21380 Savigny Le Sec"},{"value":"VILLE_364928114","text":"21390 Bierre Les Semur"},{"value":"VILLE_4261806","text":"21400 Aisey Sur Seine"},{"value":"VILLE_985029275","text":"21400 Ampilly Le Sec"},{"value":"VILLE_994268318","text":"21400 Charrey Sur Seine"},{"value":"VILLE_948252031","text":"21400 Chatillon Sur Seine"},{"value":"VILLE_130899262","text":"21400 Coulmier Le Sec"},{"value":"VILLE_621928484","text":"21400 Nod Sur Seine"},{"value":"VILLE_477891624","text":"21400 Noiron Sur Seine"},{"value":"VILLE_515692732","text":"21400 Sainte Colombe Sur Seine"},{"value":"VILLE_558399692","text":"21440 Bligny Le Sec"},{"value":"VILLE_166650546","text":"21440 Saint Seine L'abbaye"},{"value":"VILLE_813381567","text":"21450 Saint Marc Sur Seine"},{"value":"VILLE_578044291","text":"21450 Semond"},{"value":"VILLE_110069248","text":"21500 Saint Germain Les Senailly"},{"value":"VILLE_308986539","text":"21500 Senailly"},{"value":"VILLE_489267038","text":"21510 Bellenod Sur Seine"},{"value":"VILLE_975160613","text":"21510 Quemigny Sur Seine"},{"value":"VILLE_9851326","text":"21550 Ladoix Serrigny"},{"value":"VILLE_329122746","text":"21610 Saint Seine Sur Vingeanne"},{"value":"VILLE_569168914","text":"21690 Saint Germain Source Seine"},{"value":"VILLE_821500247","text":"21690 Villotte Saint Seine"},{"value":"VILLE_969288640","text":"21800 Sennecey Les Dijon"},{"value":"VILLE_149383328","text":"21820 Labergement Les Seurre"},{"value":"VILLE_759904706","text":"22160 Saint Servais"},{"value":"VILLE_987547253","text":"22250 Sevignac"},{"value":"VILLE_562301054","text":"22720 Senven Lehart"},{"value":"VILLE_280644084","text":"23160 Saint Sebastien"},{"value":"VILLE_673767633","text":"23190 La Serre Bussiere Vieille"},{"value":"VILLE_863160589","text":"23700 Sermur"},{"value":"VILLE_434568437","text":"24190 Saint Severin D'estissac"},{"value":"VILLE_46409175","text":"24230 Saint Seurin De Prats"},{"value":"VILLE_936783532","text":"24290 Sergeac"},{"value":"VILLE_224343699","text":"24310 Sencenac Puy De Fourches"},{"value":"VILLE_833664376","text":"24320 Bouteilles Saint Sebastien"},{"value":"VILLE_773862160","text":"24380 Saint Paul De Serre"},{"value":"VILLE_776828807","text":"24410 Servanches"},{"value":"VILLE_305390662","text":"24440 Saint Avit Senieur"},{"value":"VILLE_957344997","text":"24500 Serres Et Montguyard"},{"value":"VILLE_394503942","text":"24600 Segonzac"},{"value":"VILLE_618220087","text":"25110 Sechin"},{"value":"VILLE_62063814","text":"25230 Seloncourt"},{"value":"VILLE_499595805","text":"25270 Septfontaines"},{"value":"VILLE_416061940","text":"25430 Servin"},{"value":"VILLE_335906006","text":"25610 Arc Et Senans"},{"value":"VILLE_98016071","text":"25680 Montagney Servigney"},{"value":"VILLE_768106212","text":"25750 Semondans"},{"value":"VILLE_417220827","text":"25770 Serre Les Sapins"},{"value":"VILLE_977081913","text":"26340 Pennes Le Sec"},{"value":"VILLE_323214846","text":"26530 Le Grand Serre"},{"value":"VILLE_190433479","text":"26560 Sederon"},{"value":"VILLE_371301471","text":"26600 Serves Sur Rhone"},{"value":"VILLE_765168550","text":"26770 Roche Saint Secret Beconne"},{"value":"VILLE_643952686","text":"27100 Tournedos Sur Seine"},{"value":"VILLE_124846548","text":"27110 Graveron Semerville"},{"value":"VILLE_922825348","text":"27180 Saint Sebastien De Morsent"},{"value":"VILLE_202383348","text":"27190 Nagel Seez Mesnil"},{"value":"VILLE_143061885","text":"27190 Nogent Le Sec"},{"value":"VILLE_178033429","text":"27190 Sebecourt"},{"value":"VILLE_50638949","text":"27220 Serez"},{"value":"VILLE_740723152","text":"27310 Barneville Sur Seine"},{"value":"VILLE_274076678","text":"27340 Criquebeuf Sur Seine"},{"value":"VILLE_71933125","text":"27470 Serquigny"},{"value":"VILLE_905168482","text":"27500 Selles"},{"value":"VILLE_489608079","text":"27680 Quillebeuf Sur Seine"},{"value":"VILLE_501320026","text":"27700 Bernieres Sur Seine"},{"value":"VILLE_874658041","text":"27940 Courcelles Sur Seine"},{"value":"VILLE_654790294","text":"28170 Serazereux"},{"value":"VILLE_776804826","text":"28210 Senantes"},{"value":"VILLE_11143767","text":"28250 Senonches"},{"value":"VILLE_149995251","text":"28400 Trizay Coutretot Saint Serge"},{"value":"VILLE_778106977","text":"28410 Serville"},{"value":"VILLE_987643373","text":"29400 Saint Servais"},{"value":"VILLE_239687100","text":"29590 Saint Segal"},{"value":"VILLE_869563665","text":"29600 Sainte Seve"},{"value":"VILLE_277662265","text":"29990 Ile De Sein"},{"value":"VILLE_241325606","text":"30140 Saint Sebastien D'aigrefeuille"},{"value":"VILLE_537614992","text":"30210 Sernhac"},{"value":"VILLE_411170670","text":"30260 Orthoux Serignac Quilhan"},{"value":"VILLE_480406480","text":"30340 Servas"},{"value":"VILLE_647816124","text":"30350 Saint Jean De Serres"},{"value":"VILLE_117091989","text":"30450 Senechas"},{"value":"VILLE_744473962","text":"30580 Seynes"},{"value":"VILLE_227091984","text":"30700 Serviers Et Labaume"},{"value":"VILLE_218338382","text":"31160 Sengouagnet"},{"value":"VILLE_306251029","text":"31360 Sepx"},{"value":"VILLE_838014719","text":"31420 Saint Elix Seglan"},{"value":"VILLE_775577349","text":"31430 Senarens"},{"value":"VILLE_896325840","text":"31460 Segreville"},{"value":"VILLE_129957732","text":"31480 Cabanac Seguenville"},{"value":"VILLE_879717394","text":"31510 Seilhan"},{"value":"VILLE_427868685","text":"31560 Seyre"},{"value":"VILLE_565547000","text":"31580 Sedeilhac"},{"value":"VILLE_440166137","text":"31600 Seysses"},{"value":"VILLE_164789940","text":"31620 Labastide Saint Sernin"},{"value":"VILLE_292067475","text":"31840 Seilh"},{"value":"VILLE_143754159","text":"32120 Serempuy"},{"value":"VILLE_353902838","text":"32130 Seysses Saves"},{"value":"VILLE_714824620","text":"32140 Sere"},{"value":"VILLE_3849702","text":"32190 Seailles"},{"value":"VILLE_788161592","text":"32230 Blousson Serian"},{"value":"VILLE_886921215","text":"32230 Semboues"},{"value":"VILLE_800148297","text":"32260 Seissan"},{"value":"VILLE_794695873","text":"32400 Segos"},{"value":"VILLE_842194134","text":"32410 Larroque Saint Sernin"},{"value":"VILLE_322670837","text":"32450 Semezies Cachan"},{"value":"VILLE_620983737","text":"32600 Segoufielle"},{"value":"VILLE_419320877","text":"32700 Sempesserre"},{"value":"VILLE_250006209","text":"33180 Saint Seurin De Cadourne"},{"value":"VILLE_448780924","text":"33190 Saint Seve"},{"value":"VILLE_215909513","text":"33220 Saint Philippe Du Seignal"},{"value":"VILLE_556720847","text":"33390 Saint Seurin De Cursac"},{"value":"VILLE_189456202","text":"33490 Saint Martin De Sescas"},{"value":"VILLE_360252499","text":"33490 Semens"},{"value":"VILLE_490415042","text":"33540 Landerrouet Sur Segur"},{"value":"VILLE_258162177","text":"33650 Saint Selve"},{"value":"VILLE_353557636","text":"33660 Saint Seurin Sur L'isle"},{"value":"VILLE_933556308","text":"33690 Sendets"},{"value":"VILLE_915214082","text":"33710 Saint Seurin De Bourg"},{"value":"VILLE_135359293","text":"33820 Pleine Selve"},{"value":"VILLE_141173842","text":"34200 Sete"},{"value":"VILLE_716262331","text":"34290 Servian"},{"value":"VILLE_121972277","text":"34380 Causse De La Selle"},{"value":"VILLE_841063392","text":"34400 Saint Series"},{"value":"VILLE_331676317","text":"34410 Serignan"},{"value":"VILLE_807624867","text":"35130 Availles Sur Seiche"},{"value":"VILLE_906200576","text":"35130 La Selle Guerchaise"},{"value":"VILLE_336326768","text":"35133 La Selle En Luitre"},{"value":"VILLE_330186737","text":"35150 Pire Sur Seiche"},{"value":"VILLE_323473525","text":"35230 Noyal Chatillon Sur Seiche"},{"value":"VILLE_801376440","text":"35320 Le Sel De Bretagne"},{"value":"VILLE_917722520","text":"35330 Saint Seglin"},{"value":"VILLE_901629824","text":"35370 Gennes Sur Seiche"},{"value":"VILLE_840701875","text":"35460 La Selle En Cogles"},{"value":"VILLE_480395403","text":"35490 Sens De Bretagne"},{"value":"VILLE_989016742","text":"35510 Cesson Sevigne"},{"value":"VILLE_218404168","text":"35530 Servon Sur Vilaine"},{"value":"VILLE_899689639","text":"35580 Saint Senoux"},{"value":"VILLE_441493995","text":"35770 Vern Sur Seiche"},{"value":"VILLE_496546908","text":"36100 Segry"},{"value":"VILLE_510078953","text":"36160 Sainte Severe Sur Indre"},{"value":"VILLE_335524182","text":"36180 Selles Sur Nahon"},{"value":"VILLE_649718124","text":"36210 Semblecay"},{"value":"VILLE_932148907","text":"36230 Neuvy Saint Sepulchre"},{"value":"VILLE_214397987","text":"37310 Dolus Le Sec"},{"value":"VILLE_740865586","text":"37360 Semblancay"},{"value":"VILLE_756082201","text":"37500 Seuilly"},{"value":"VILLE_339377146","text":"37600 Saint Senoch"},{"value":"VILLE_363263218","text":"37600 Sennevieres"},{"value":"VILLE_267083471","text":"37800 Sepmes"},{"value":"VILLE_18239243","text":"38170 Seyssinet Pariset"},{"value":"VILLE_8740801","text":"38180 Seyssins"},{"value":"VILLE_330350841","text":"38200 Serpaize"},{"value":"VILLE_466680206","text":"38200 Seyssuel"},{"value":"VILLE_531470345","text":"38220 Saint Barthelemy De Sechilienne"},{"value":"VILLE_735797918","text":"38220 Sechilienne"},{"value":"VILLE_180625300","text":"38260 Semons"},{"value":"VILLE_886133745","text":"38300 Serezin De La Tour"},{"value":"VILLE_676446685","text":"38470 Serre Nerpol"},{"value":"VILLE_260602130","text":"38510 Sermerieu"},{"value":"VILLE_544754320","text":"38710 Saint Sebastien"},{"value":"VILLE_652828719","text":"38780 Septeme"},{"value":"VILLE_355946969","text":"39120 Seligney"},{"value":"VILLE_15319716","text":"39120 Sergenon"},{"value":"VILLE_138256892","text":"39140 Ruffey Sur Seille"},{"value":"VILLE_42916939","text":"39160 Senaud"},{"value":"VILLE_787518921","text":"39210 Blois Sur Seille"},{"value":"VILLE_663052134","text":"39210 Ladoye Sur Seille"},{"value":"VILLE_75693420","text":"39210 Nevy Sur Seille"},{"value":"VILLE_791755882","text":"39230 Chene Sec"},{"value":"VILLE_775761285","text":"39230 Sellieres"},{"value":"VILLE_658613251","text":"39230 Sergenaux"},{"value":"VILLE_645872197","text":"39230 Vers Sous Sellieres"},{"value":"VILLE_608990422","text":"39310 Septmoncel"},{"value":"VILLE_967340349","text":"39700 Sermange"},{"value":"VILLE_911835430","text":"39700 Serre Les Moulieres"},{"value":"VILLE_950053098","text":"40180 Seyresse"},{"value":"VILLE_121485912","text":"40320 Miramont Sensacq"},{"value":"VILLE_435131531","text":"40390 Saint Andre De Seignanx"},{"value":"VILLE_44472923","text":"40390 Saint Martin De Seignanx"},{"value":"VILLE_263572759","text":"40420 Le Sen"},{"value":"VILLE_145826970","text":"40500 Saint Sever"},{"value":"VILLE_413614418","text":"40510 Seignosse"},{"value":"VILLE_178073039","text":"40700 Serres Gaston"},{"value":"VILLE_127194465","text":"40700 Serreslous Et Arribans"},{"value":"VILLE_482081981","text":"41100 Selommes"},{"value":"VILLE_352008471","text":"41110 Seigy"},{"value":"VILLE_185684115","text":"41120 Seur"},{"value":"VILLE_848632826","text":"41130 Selles Sur Cher"},{"value":"VILLE_153813419","text":"41150 Seillac"},{"value":"VILLE_328355908","text":"41160 Semerville"},{"value":"VILLE_435949261","text":"41300 Selles Saint Denis"},{"value":"VILLE_2733068","text":"41500 Seris"},{"value":"VILLE_960106211","text":"42460 Sevelinges"},{"value":"VILLE_178161658","text":"43140 La Seauve Sur Semene"},{"value":"VILLE_312354151","text":"43160 Saint Pal De Senouire"},{"value":"VILLE_565304837","text":"43160 Sembadel"},{"value":"VILLE_254636714","text":"43510 Seneujols"},{"value":"VILLE_300969220","text":"44230 Saint Sebastien Sur Loire"},{"value":"VILLE_240472748","text":"44530 Severac"},{"value":"VILLE_2429550","text":"44690 Maisdon Sur Sevre"},{"value":"VILLE_863331886","text":"45210 La Chapelle Saint Sepulcre"},{"value":"VILLE_690333622","text":"45210 La Selle En Hermoy"},{"value":"VILLE_319065670","text":"45210 La Selle Sur Le Bied"},{"value":"VILLE_587737097","text":"45240 Sennely"},{"value":"VILLE_724255504","text":"45300 Sermaises"},{"value":"VILLE_3231999","text":"45400 Semoy"},{"value":"VILLE_858345230","text":"45530 Seichebrieres"},{"value":"VILLE_903339367","text":"46210 Senaillac Latronquiere"},{"value":"VILLE_427660452","text":"46240 Seniergues"},{"value":"VILLE_424985721","text":"46360 Senaillac Lauzes"},{"value":"VILLE_281063589","text":"46700 Serignac"},{"value":"VILLE_714528513","text":"47120 Saint Sernin"},{"value":"VILLE_550943715","text":"47310 Serignac Sur Garonne"},{"value":"VILLE_251995614","text":"47350 Seyches"},{"value":"VILLE_53183629","text":"47360 Sembas"},{"value":"VILLE_851784911","text":"47410 Segalas"},{"value":"VILLE_891581801","text":"47410 Serignac Peboudou"},{"value":"VILLE_564465319","text":"47430 Senestis"},{"value":"VILLE_33838849","text":"48000 Servieres"},{"value":"VILLE_762948","text":"48700 Serverette"},{"value":"VILLE_627856283","text":"49140 Seiches Sur Le Loir"},{"value":"VILLE_517980311","text":"49140 Sermaise"},{"value":"VILLE_715586865","text":"49280 La Seguiniere"},{"value":"VILLE_95678148","text":"49350 Saint Georges Des Sept Voies"},{"value":"VILLE_400497351","text":"49500 Segre"},{"value":"VILLE_446654558","text":"50170 Servon"},{"value":"VILLE_958639462","text":"50190 Saint Germain Sur Seves"},{"value":"VILLE_603822010","text":"50190 Saint Sebastien De Raids"},{"value":"VILLE_514630798","text":"50200 Servigny"},{"value":"VILLE_204216747","text":"50240 Saint Senier De Beuvron"},{"value":"VILLE_653757569","text":"50270 Senoville"},{"value":"VILLE_203022089","text":"50300 Saint Senier Sous Avranches"},{"value":"VILLE_618293664","text":"50480 Sebeville"},{"value":"VILLE_43246639","text":"50810 La Barre De Semilly"},{"value":"VILLE_534094795","text":"50810 Saint Pierre De Semilly"},{"value":"VILLE_799699738","text":"51120 Les Essarts Les Sezanne"},{"value":"VILLE_392927056","text":"51120 Sezanne"},{"value":"VILLE_658391257","text":"51170 Serzy Et Prin"},{"value":"VILLE_951892703","text":"51250 Sermaize Les Bains"},{"value":"VILLE_344104161","text":"51250 Villers Le Sec"},{"value":"VILLE_472845192","text":"51260 Conflans Sur Seine"},{"value":"VILLE_569171302","text":"51260 Marcilly Sur Seine"},{"value":"VILLE_998123134","text":"51400 Sept Saulx"},{"value":"VILLE_130370607","text":"51490 Selles"},{"value":"VILLE_697284","text":"51500 Sermiers"},{"value":"VILLE_672830751","text":"51500 Ville En Selve"},{"value":"VILLE_236140375","text":"51800 Servon Melzicourt"},{"value":"VILLE_470243315","text":"52000 Semoutiers Montsaon"},{"value":"VILLE_766294695","text":"52000 Villiers Le Sec"},{"value":"VILLE_628620418","text":"52310 Ormoy Les Sexfontaines"},{"value":"VILLE_820221060","text":"52330 Sexfontaines"},{"value":"VILLE_74270623","text":"52400 Serqueux"},{"value":"VILLE_446384963","text":"52700 Semilly"},{"value":"VILLE_82771929","text":"53340 Epineux Le Seguin"},{"value":"VILLE_572912436","text":"53390 Senonnes"},{"value":"VILLE_506938926","text":"53800 La Selle Craonnaise"},{"value":"VILLE_699401561","text":"54150 Norroy Le Sec"},{"value":"VILLE_191346389","text":"54170 Selaincourt"},{"value":"VILLE_85819670","text":"54280 Brin Sur Seille"},{"value":"VILLE_784206043","text":"54280 Moncel Sur Seille"},{"value":"VILLE_242643369","text":"54280 Seichamps"},{"value":"VILLE_366996255","text":"54370 Serres"},{"value":"VILLE_442981020","text":"54470 Seicheprey"},{"value":"VILLE_931963618","text":"54550 Sexey Aux Forges"},{"value":"VILLE_775009924","text":"54560 Serrouville"},{"value":"VILLE_197340707","text":"54610 Abaucourt Sur Seille"},{"value":"VILLE_146808831","text":"54610 Mailly Sur Seille"},{"value":"VILLE_947346433","text":"54700 Morville Sur Seille"},{"value":"VILLE_944320233","text":"54700 Port Sur Seille"},{"value":"VILLE_21131102","text":"54760 Bey Sur Seille"},{"value":"VILLE_212799017","text":"54830 Seranville"},{"value":"VILLE_513645374","text":"54840 Sexey Les Bois"},{"value":"VILLE_341194918","text":"54840 Villey Le Sec"},{"value":"VILLE_700371397","text":"55000 Seigneulles"},{"value":"VILLE_43517645","text":"55140 Sepvigny"},{"value":"VILLE_962715443","text":"55220 Senoncourt Les Maujouy"},{"value":"VILLE_522359596","text":"55230 Senon"},{"value":"VILLE_367520916","text":"55250 Seuil D'argonne"},{"value":"VILLE_699698530","text":"55270 Septsarges"},{"value":"VILLE_787360103","text":"55300 Seuzey"},{"value":"VILLE_282628182","text":"55500 Villers Le Sec"},{"value":"VILLE_260427401","text":"55600 Ire Le Sec"},{"value":"VILLE_146971286","text":"56120 Saint Servant"},{"value":"VILLE_627307577","text":"56160 Seglien"},{"value":"VILLE_248170778","text":"56460 Serent"},{"value":"VILLE_819395405","text":"56860 Sene"},{"value":"VILLE_306332968","text":"57280 Semecourt"},{"value":"VILLE_139136145","text":"57290 Seremange Erzange"},{"value":"VILLE_326625772","text":"57420 Coin Sur Seille"},{"value":"VILLE_513934602","text":"57420 Secourt"},{"value":"VILLE_230256100","text":"57455 Seingbouse"},{"value":"VILLE_335841468","text":"57530 Servigny Les Raville"},{"value":"VILLE_443488681","text":"57590 Aboncourt Sur Seille"},{"value":"VILLE_68960295","text":"57590 Aulnois Sur Seille"},{"value":"VILLE_432579913","text":"57590 Malaucourt Sur Seille"},{"value":"VILLE_798903847","text":"57630 Haraucourt Sur Seille"},{"value":"VILLE_646901594","text":"57630 Vic Sur Seille"},{"value":"VILLE_207279227","text":"57640 Servigny Les Sainte Barbe"},{"value":"VILLE_183918258","text":"58000 Sermoise Sur Loire"},{"value":"VILLE_226640230","text":"58210 Villiers Le Sec"},{"value":"VILLE_517271929","text":"58230 Montsauche Les Settons"},{"value":"VILLE_555862502","text":"58250 Saint Seine"},{"value":"VILLE_91460165","text":"58290 Sermages"},{"value":"VILLE_64156050","text":"58360 Semelay"},{"value":"VILLE_519594561","text":"59113 Seclin"},{"value":"VILLE_888734433","text":"59127 Walincourt Selvigny"},{"value":"VILLE_307815748","text":"59139 Noyelles Les Seclin"},{"value":"VILLE_991817665","text":"59173 Sercus"},{"value":"VILLE_135904587","text":"59174 La Sentinelle"},{"value":"VILLE_88956007","text":"59269 Sepmeries"},{"value":"VILLE_943907046","text":"59282 Noyelles Sur Selle"},{"value":"VILLE_835901050","text":"59296 Avesnes Le Sec"},{"value":"VILLE_28730830","text":"59320 Erquinghem Le Sec"},{"value":"VILLE_800658735","text":"59320 Sequedin"},{"value":"VILLE_151530135","text":"59400 Seranvillers Forenville"},{"value":"VILLE_255146654","text":"59440 Semeries"},{"value":"VILLE_663574599","text":"59440 Semousies"},{"value":"VILLE_960136197","text":"59990 Sebourg"},{"value":"VILLE_514885392","text":"60120 Serevillers"},{"value":"VILLE_504449979","text":"60134 Villers Saint Sepulcre"},{"value":"VILLE_473556609","text":"60240 Enencourt Le Sec"},{"value":"VILLE_303684679","text":"60240 Senots"},{"value":"VILLE_161430857","text":"60240 Serans"},{"value":"VILLE_999828397","text":"60300 Senlis"},{"value":"VILLE_860253667","text":"60330 Lagny Le Sec"},{"value":"VILLE_568138666","text":"60400 Sempigny"},{"value":"VILLE_302071571","text":"60400 Sermaize"},{"value":"VILLE_513445331","text":"60520 La Chapelle En Serval"},{"value":"VILLE_928374510","text":"60590 Serifontaine"},{"value":"VILLE_120948212","text":"60650 Senantes"},{"value":"VILLE_587303352","text":"60800 Sery Magneval"},{"value":"VILLE_466798040","text":"60840 Breuil Le Sec"},{"value":"VILLE_102190870","text":"61100 La Selle La Forge"},{"value":"VILLE_809563184","text":"61100 Segrie Fontaine"},{"value":"VILLE_554626314","text":"61130 Serigny"},{"value":"VILLE_194386947","text":"61150 Sentilly"},{"value":"VILLE_980456111","text":"61150 Serans"},{"value":"VILLE_416443039","text":"61150 Sevrai"},{"value":"VILLE_709890244","text":"61200 Sevigny"},{"value":"VILLE_718236823","text":"61250 Semalle"},{"value":"VILLE_956611549","text":"61330 Sept Forges"},{"value":"VILLE_254234489","text":"61500 La Chapelle Pres Sees"},{"value":"VILLE_170947136","text":"61500 Neuville Pres Sees"},{"value":"VILLE_673756020","text":"61500 Sees"},{"value":"VILLE_336298515","text":"61560 Saint Ouen De Secherouvre"},{"value":"VILLE_290714776","text":"62130 Herlin Le Sec"},{"value":"VILLE_124389921","text":"62170 Sempy"},{"value":"VILLE_106022719","text":"62240 Selles"},{"value":"VILLE_526911096","text":"62240 Senlecques"},{"value":"VILLE_686214089","text":"62270 Sericourt"},{"value":"VILLE_368393108","text":"62310 Senlis"},{"value":"VILLE_783151587","text":"62380 Bayenghem Les Seninghem"},{"value":"VILLE_359751896","text":"62380 Seninghem"},{"value":"VILLE_269470774","text":"62380 Setques"},{"value":"VILLE_116059044","text":"62530 Gouy Servins"},{"value":"VILLE_50054751","text":"62530 Servins"},{"value":"VILLE_823848103","text":"62870 Buire Le Sec"},{"value":"VILLE_725268551","text":"62910 Serques"},{"value":"VILLE_504293907","text":"63120 Sermentizon"},{"value":"VILLE_595854479","text":"63190 Seychalles"},{"value":"VILLE_769790094","text":"63560 Servant"},{"value":"VILLE_109398257","text":"64121 Serres Castet"},{"value":"VILLE_765169860","text":"64160 Sedze Maubecq"},{"value":"VILLE_387871514","text":"64160 Sedzere"},{"value":"VILLE_665727916","text":"64160 Serres Morlaas"},{"value":"VILLE_103729255","text":"64160 Sevignacq"},{"value":"VILLE_601419169","text":"64170 Serres Sainte Marie"},{"value":"VILLE_164633994","text":"64260 Sevignacq Meyracq"},{"value":"VILLE_525979131","text":"64320 Sendets"},{"value":"VILLE_558609039","text":"64350 Semeacq Blachon"},{"value":"VILLE_463119290","text":"64410 Seby"},{"value":"VILLE_172830615","text":"64460 Bentayou Seree"},{"value":"VILLE_75835019","text":"65100 Segus"},{"value":"VILLE_3558700","text":"65100 Sere Lanso"},{"value":"VILLE_340163100","text":"65120 Esquieze Sere"},{"value":"VILLE_994081533","text":"65120 Sers"},{"value":"VILLE_561979823","text":"65140 Saint Sever De Rustan"},{"value":"VILLE_93835516","text":"65140 Segalas"},{"value":"VILLE_105908495","text":"65140 Senac"},{"value":"VILLE_4752176","text":"65150 Seich"},{"value":"VILLE_792609613","text":"65220 Sere Rustaing"},{"value":"VILLE_903327205","text":"65320 Seron"},{"value":"VILLE_160832932","text":"65330 Sentous"},{"value":"VILLE_916950900","text":"65400 Sere En Lavedan"},{"value":"VILLE_453969923","text":"65600 Semeac"},{"value":"VILLE_156553769","text":"66230 Serralongue"},{"value":"VILLE_779046478","text":"66360 Serdinya"},{"value":"VILLE_615438170","text":"67160 Seebach"},{"value":"VILLE_758308854","text":"67230 Sermersheim"},{"value":"VILLE_477151443","text":"67470 Eberbach Seltz"},{"value":"VILLE_883018958","text":"67470 Schaffhouse Pres Seltz"},{"value":"VILLE_87385504","text":"67470 Seltz"},{"value":"VILLE_993062941","text":"67600 Selestat"},{"value":"VILLE_20002840","text":"67770 Sessenheim"},{"value":"VILLE_454201787","text":"68290 Sewen"},{"value":"VILLE_117118537","text":"68580 Seppois Le Bas"},{"value":"VILLE_660774165","text":"68580 Seppois Le Haut"},{"value":"VILLE_848979403","text":"68780 Sentheim"},{"value":"VILLE_603808960","text":"69360 Serezin Du Rhone"},{"value":"VILLE_646932108","text":"69420 Tupin Et Semons"},{"value":"VILLE_795762856","text":"70000 Echenoz Le Sec"},{"value":"VILLE_222643928","text":"70000 Villers Le Sec"},{"value":"VILLE_503203849","text":"70110 Senargent Mignafans"},{"value":"VILLE_548498426","text":"70120 Semmadon"},{"value":"VILLE_32558552","text":"70130 Seveux"},{"value":"VILLE_156943186","text":"70160 Senoncourt"},{"value":"VILLE_808143902","text":"70210 Selles"},{"value":"VILLE_848164632","text":"70240 Servigney"},{"value":"VILLE_82463465","text":"70400 Secenans"},{"value":"VILLE_462711196","text":"70440 Servance"},{"value":"VILLE_563668414","text":"70800 Saint Loup Sur Semouse"},{"value":"VILLE_757867329","text":"71100 Sevrey"},{"value":"VILLE_274915619","text":"71110 Semur En Brionnais"},{"value":"VILLE_287677605","text":"71200 Saint Sernin Du Bois"},{"value":"VILLE_858573715","text":"71240 Sennecey Le Grand"},{"value":"VILLE_466091428","text":"71260 Senozan"},{"value":"VILLE_199186809","text":"71270 Mont Les Seurre"},{"value":"VILLE_788216019","text":"71290 Huilly Sur Seille"},{"value":"VILLE_482348111","text":"71310 Serley"},{"value":"VILLE_246269721","text":"71310 Serrigny En Bresse"},{"value":"VILLE_842712105","text":"71330 Sens Sur Seille"},{"value":"VILLE_265245170","text":"71350 Sermesse"},{"value":"VILLE_329283541","text":"71440 Savigny Sur Seille"},{"value":"VILLE_757267080","text":"71460 Sercy"},{"value":"VILLE_624352320","text":"71510 Saint Sernin Du Plain"},{"value":"VILLE_783176664","text":"71960 Serrieres"},{"value":"VILLE_252145481","text":"72170 Segrie"},{"value":"VILLE_234567414","text":"72390 Semur En Vallon"},{"value":"VILLE_277096186","text":"72400 Boesse Le Sec"},{"value":"VILLE_84581713","text":"73290 La Motte Servolex"},{"value":"VILLE_999827270","text":"73310 Serrieres En Chautagne"},{"value":"VILLE_825218708","text":"73700 Seez"},{"value":"VILLE_118189013","text":"74210 Seythenex"},{"value":"VILLE_750109322","text":"74230 Serraval"},{"value":"VILLE_128546142","text":"74270 Chene En Semine"},{"value":"VILLE_259178988","text":"74310 Servoz"},{"value":"VILLE_611613969","text":"74320 Sevrier"},{"value":"VILLE_558734482","text":"74430 Seytroux"},{"value":"VILLE_209828369","text":"74600 Seynod"},{"value":"VILLE_350213987","text":"74910 Seyssel"},{"value":"VILLE_73605664","text":"76110 Daubeuf Serville"},{"value":"VILLE_661647900","text":"76113 Hautot Sur Seine"},{"value":"VILLE_425536851","text":"76116 Servaville Salmonville"},{"value":"VILLE_25482010","text":"76260 Sept Meules"},{"value":"VILLE_597275457","text":"76400 Senneville Sur Fecamp"},{"value":"VILLE_283235803","text":"76440 Serqueux"},{"value":"VILLE_822971162","text":"76460 Pleine Seve"},{"value":"VILLE_788806632","text":"76480 Berville Sur Seine"},{"value":"VILLE_514023306","text":"76530 Yville Sur Seine"},{"value":"VILLE_521219674","text":"76850 Sevis"},{"value":"VILLE_886391443","text":"76940 La Mailleraye Sur Seine"},{"value":"VILLE_220221722","text":"77000 Livry Sur Seine"},{"value":"VILLE_126379347","text":"77114 Noyen Sur Seine"},{"value":"VILLE_172969948","text":"77114 Villiers Sur Seine"},{"value":"VILLE_784705214","text":"77126 Chatenay Sur Seine"},{"value":"VILLE_563433196","text":"77130 Marolles Sur Seine"},{"value":"VILLE_759359892","text":"77130 Varennes Sur Seine"},{"value":"VILLE_913101777","text":"77170 Servon"},{"value":"VILLE_46893063","text":"77171 Melz Sur Seine"},{"value":"VILLE_162207260","text":"77240 Seine Port"},{"value":"VILLE_175779063","text":"77260 Sept Sorts"},{"value":"VILLE_571591145","text":"77350 Le Mee Sur Seine"},{"value":"VILLE_954198458","text":"77430 Champagne Sur Seine"},{"value":"VILLE_507029265","text":"77480 Bray Sur Seine"},{"value":"VILLE_495099000","text":"77480 Grisy Sur Seine"},{"value":"VILLE_781168089","text":"77480 Mouy Sur Seine"},{"value":"VILLE_440252082","text":"77480 Passy Sur Seine"},{"value":"VILLE_625057918","text":"77670 Vernou La Celle Sur Seine"},{"value":"VILLE_534587236","text":"77700 Serris"},{"value":"VILLE_962612482","text":"77710 Chevry En Sereine"},{"value":"VILLE_608993500","text":"77870 Vulaines Sur Seine"},{"value":"VILLE_595809968","text":"77920 Samois Sur Seine"},{"value":"VILLE_698759683","text":"78111 Dammartin En Serve"},{"value":"VILLE_264631621","text":"78250 Mezy Sur Seine"},{"value":"VILLE_134645135","text":"78270 Bonnieres Sur Seine"},{"value":"VILLE_871395660","text":"78270 Mousseaux Sur Seine"},{"value":"VILLE_458786095","text":"78290 Croissy Sur Seine"},{"value":"VILLE_202675250","text":"78410 Flins Sur Seine"},{"value":"VILLE_902988775","text":"78420 Carrieres Sur Seine"},{"value":"VILLE_870598630","text":"78480 Verneuil Sur Seine"},{"value":"VILLE_902029374","text":"78510 Triel Sur Seine"},{"value":"VILLE_132036326","text":"78670 Villennes Sur Seine"},{"value":"VILLE_84772069","text":"78710 Rosny Sur Seine"},{"value":"VILLE_519885262","text":"78720 Senlisse"},{"value":"VILLE_759532654","text":"78740 Vaux Sur Seine"},{"value":"VILLE_239755993","text":"78790 Septeuil"},{"value":"VILLE_383416279","text":"78970 Mezieres Sur Seine"},{"value":"VILLE_603457861","text":"79120 Sepvret"},{"value":"VILLE_120471376","text":"79130 Secondigny"},{"value":"VILLE_405066092","text":"79170 Secondigne Sur Belle"},{"value":"VILLE_120233443","text":"79170 Seligne"},{"value":"VILLE_340786569","text":"79380 La Foret Sur Sevre"},{"value":"VILLE_484932607","text":"79380 Saint Andre Sur Sevre"},{"value":"VILLE_547893243","text":"79700 Saint Amand Sur Sevre"},{"value":"VILLE_523454640","text":"80140 Fontaine Le Sec"},{"value":"VILLE_409197374","text":"80140 Senarpont"},{"value":"VILLE_563263649","text":"80160 Sentelie"},{"value":"VILLE_415947260","text":"80220 Bouillancourt En Sery"},{"value":"VILLE_43062401","text":"80250 Quiry Le Sec"},{"value":"VILLE_182442033","text":"80290 Sainte Segree"},{"value":"VILLE_728276768","text":"80300 Senlis Le Sec"},{"value":"VILLE_783199914","text":"80480 Bacouel Sur Selle"},{"value":"VILLE_880436662","text":"80480 Vers Sur Selles"},{"value":"VILLE_111156638","text":"80540 Seux"},{"value":"VILLE_19452064","text":"80800 Sailly Le Sec"},{"value":"VILLE_503576877","text":"81170 Lacapelle Segalar"},{"value":"VILLE_655235946","text":"81220 Servies"},{"value":"VILLE_206145465","text":"81350 Serenac"},{"value":"VILLE_829965147","text":"81500 Massac Seran"},{"value":"VILLE_944645732","text":"81530 Senaux"},{"value":"VILLE_897159476","text":"81570 Semalens"},{"value":"VILLE_247129681","text":"81600 Senouillac"},{"value":"VILLE_482485311","text":"81640 Le Segur"},{"value":"VILLE_262962631","text":"81700 Saint Sernin Les Lavaur"},{"value":"VILLE_150533938","text":"81990 Le Sequestre"},{"value":"VILLE_841485135","text":"82240 Septfonds"},{"value":"VILLE_538952053","text":"82330 Verfeil Sur Seye"},{"value":"VILLE_349574321","text":"82500 Serignac"},{"value":"VILLE_949467601","text":"83440 Seillans"},{"value":"VILLE_509655156","text":"83470 Seillons Source D'argens"},{"value":"VILLE_410762965","text":"83500 La Seyne Sur Mer"},{"value":"VILLE_380226464","text":"84110 Seguret"},{"value":"VILLE_356356001","text":"84830 Serignan Du Comtat"},{"value":"VILLE_627625107","text":"85200 Serigne"},{"value":"VILLE_347903525","text":"85240 Puy De Serre"},{"value":"VILLE_615697990","text":"85290 Mortagne Sur Sevre"},{"value":"VILLE_844580505","text":"85290 Saint Laurent Sur Sevre"},{"value":"VILLE_133108223","text":"85600 Treize Septiers"},{"value":"VILLE_327656232","text":"85700 La Pommeraie Sur Sevre"},{"value":"VILLE_829286800","text":"86100 Senille"},{"value":"VILLE_907872736","text":"86170 Champigny Le Sec"},{"value":"VILLE_864101718","text":"86230 Serigny"},{"value":"VILLE_439029261","text":"86300 Paizay Le Sec"},{"value":"VILLE_174802179","text":"86350 Saint Secondin"},{"value":"VILLE_359265849","text":"86510 Champagne Le Sec"},{"value":"VILLE_40874883","text":"86800 Sevres Anxaumont"},{"value":"VILLE_467481300","text":"87330 Montrol Senard"},{"value":"VILLE_889212135","text":"87620 Sereilhac"},{"value":"VILLE_609252710","text":"88140 Dombrot Le Sec"},{"value":"VILLE_779991619","text":"88210 Menil De Senones"},{"value":"VILLE_418546053","text":"88210 Senones"},{"value":"VILLE_576558733","text":"88260 Senonges"},{"value":"VILLE_630696497","text":"88320 Senaide"},{"value":"VILLE_470327484","text":"88320 Serecourt"},{"value":"VILLE_310381502","text":"88320 Serocourt"},{"value":"VILLE_484259824","text":"88600 Sercoeur"},{"value":"VILLE_670609364","text":"88630 Seraumont"},{"value":"VILLE_709076872","text":"88640 Barbey Seroux"},{"value":"VILLE_97234562","text":"88800 Monthureux Le Sec"},{"value":"VILLE_553938509","text":"88800 Valleroy Le Sec"},{"value":"VILLE_423599431","text":"89100 Sens"},{"value":"VILLE_65268905","text":"89116 Sepeaux"},{"value":"VILLE_600012788","text":"89140 Saint Serotin"},{"value":"VILLE_779669571","text":"89140 Serbonnes"},{"value":"VILLE_620567735","text":"89140 Sergines"},{"value":"VILLE_142928059","text":"89160 Sennevoy Le Bas"},{"value":"VILLE_396813910","text":"89160 Sennevoy Le Haut"},{"value":"VILLE_312115417","text":"89200 Sermizelles"},{"value":"VILLE_568623020","text":"89220 Rogny Les Sept Ecluses"},{"value":"VILLE_996052473","text":"89250 Seignelay"},{"value":"VILLE_14224897","text":"89270 Sery"},{"value":"VILLE_875947458","text":"89310 Annay Sur Serein"},{"value":"VILLE_363002901","text":"89310 Poilly Sur Serein"},{"value":"VILLE_1248340","text":"89440 L'isle Sur Serein"},{"value":"VILLE_339793996","text":"89440 Precy Le Sec"},{"value":"VILLE_99168378","text":"89560 Merry Sec"},{"value":"VILLE_375268980","text":"89560 Sementron"},{"value":"VILLE_211969780","text":"89700 Serrigny"},{"value":"VILLE_180519850","text":"89710 Senan"},{"value":"VILLE_665414833","text":"89800 Chemilly Sur Serein"},{"value":"VILLE_29567248","text":"90100 Villars Le Sec"},{"value":"VILLE_395492528","text":"90300 Sermamagny"},{"value":"VILLE_497696216","text":"90400 Sevenans"},{"value":"VILLE_403133115","text":"91250 Morsang Sur Seine"},{"value":"VILLE_829615595","text":"91250 Saintry Sur Seine"},{"value":"VILLE_572673961","text":"91270 Vigneux Sur Seine"},{"value":"VILLE_645214590","text":"91450 Soisy Sur Seine"},{"value":"VILLE_915971664","text":"91480 Quincy Sous Senart"},{"value":"VILLE_934064745","text":"91530 Sermaise"},{"value":"VILLE_479588541","text":"91860 Epinay Sous Senart"},{"value":"VILLE_992949470","text":"91870 Boissy Le Sec"},{"value":"VILLE_108718120","text":"92200 Neuilly Sur Seine"},{"value":"VILLE_35690764","text":"92310 Sevres"},{"value":"VILLE_768954813","text":"92600 Asnieres Sur Seine"},{"value":"VILLE_469935611","text":"93130 Noisy Le Sec"},{"value":"VILLE_896956789","text":"93270 Sevran"},{"value":"VILLE_922864921","text":"93380 Pierrefitte Sur Seine"},{"value":"VILLE_240977289","text":"93800 Epinay Sur Seine"},{"value":"VILLE_201911747","text":"94200 Ivry Sur Seine"},{"value":"VILLE_214692734","text":"94400 Vitry Sur Seine"},{"value":"VILLE_58924241","text":"94480 Ablon Sur Seine"},{"value":"VILLE_931691312","text":"95270 Seugy"},{"value":"VILLE_869004934","text":"95450 Seraincourt"},{"value":"VILLE_958139807","text":"95530 La Frette Sur Seine"},{"value":"VILLE_681658083","text":"95720 Villiers Le Sec"}]