[{"value":"VILLE_526495686","text":"01110 Hauteville Lompnes"},{"value":"VILLE_214950792","text":"01250 Hautecourt Romaneche"},{"value":"VILLE_692869548","text":"02100 Harly"},{"value":"VILLE_516912186","text":"02120 Hauteville"},{"value":"VILLE_297130965","text":"02140 Harcigny"},{"value":"VILLE_887517039","text":"02140 Hary"},{"value":"VILLE_535916774","text":"02140 Haution"},{"value":"VILLE_647475781","text":"02210 Hartennes Et Taux"},{"value":"VILLE_304582149","text":"02240 Brissy Hamegicourt"},{"value":"VILLE_70558733","text":"02420 Hargicourt"},{"value":"VILLE_314486572","text":"02480 Happencourt"},{"value":"VILLE_454494783","text":"02510 Hannapes"},{"value":"VILLE_416802017","text":"02600 Haramont"},{"value":"VILLE_837646027","text":"02810 Hautevesnes"},{"value":"VILLE_459022657","text":"02820 Mauregny En Haye"},{"value":"VILLE_890470947","text":"03270 Hauterive"},{"value":"VILLE_582995563","text":"03340 La Ferte Hauterive"},{"value":"VILLE_381427076","text":"04170 Thorame Haute"},{"value":"VILLE_283125558","text":"04380 Hautes Duyes"},{"value":"VILLE_130263168","text":"04420 Prads Haute Bleone"},{"value":"VILLE_817602415","text":"05140 La Haute Beaume"},{"value":"VILLE_128473812","text":"08090 Ham Les Moines"},{"value":"VILLE_424149858","text":"08090 Haudrecy"},{"value":"VILLE_467337018","text":"08150 Harcy"},{"value":"VILLE_159092421","text":"08160 Hannogne Saint Martin"},{"value":"VILLE_36647875","text":"08170 Hargnies"},{"value":"VILLE_607486182","text":"08170 Haybes"},{"value":"VILLE_760338681","text":"08220 Hannogne Saint Remy"},{"value":"VILLE_121634049","text":"08240 Harricourt"},{"value":"VILLE_297191275","text":"08260 Flaignes Havys"},{"value":"VILLE_581066489","text":"08290 Hannappes"},{"value":"VILLE_203997321","text":"08300 Hauteville"},{"value":"VILLE_992871907","text":"08310 Hauvine"},{"value":"VILLE_96076484","text":"08430 Hagnicourt"},{"value":"VILLE_345009485","text":"08450 Haraucourt"},{"value":"VILLE_492385601","text":"08600 Ham Sur Meuse"},{"value":"VILLE_943942412","text":"08800 Haulme"},{"value":"VILLE_594110201","text":"08800 Les Hautes Rivieres"},{"value":"VILLE_125815081","text":"10140 Montmartin Le Haut"},{"value":"VILLE_39531649","text":"10290 Bercenay Le Hayer"},{"value":"VILLE_358367228","text":"10290 Marcilly Le Hayer"},{"value":"VILLE_339564972","text":"10500 Hampigny"},{"value":"VILLE_46385","text":"12200 Morlhon Le Haut"},{"value":"VILLE_227852192","text":"12300 Livinhac Le Haut"},{"value":"VILLE_861049693","text":"14140 La Chapelle Haute Grue"},{"value":"VILLE_375459642","text":"14220 Cesny Bois Halbout"},{"value":"VILLE_198264515","text":"14220 Hamars"},{"value":"VILLE_486875352","text":"14220 Thury Harcourt"},{"value":"VILLE_920402237","text":"14350 La Ferriere Harang"},{"value":"VILLE_999228244","text":"17160 Haimps"},{"value":"VILLE_384359747","text":"19220 Bassignac Le Haut"},{"value":"VILLE_387592775","text":"19340 Lamaziere Haute"},{"value":"VILLE_540565707","text":"19400 Hautefage"},{"value":"VILLE_831654199","text":"21110 Tart Le Haut"},{"value":"VILLE_609535392","text":"21121 Hauteville Les Dijon"},{"value":"VILLE_155895766","text":"21150 Hauteroche"},{"value":"VILLE_494448936","text":"21540 Blaisy Haut"},{"value":"VILLE_248272239","text":"22320 La Harmoye"},{"value":"VILLE_677709253","text":"22320 Le Haut Corlay"},{"value":"VILLE_145276490","text":"22800 Plaine Haute"},{"value":"VILLE_670704765","text":"24300 Hautefaye"},{"value":"VILLE_397681977","text":"24390 Hautefort"},{"value":"VILLE_192318903","text":"25580 Hautepierre Le Chatelet"},{"value":"VILLE_307276520","text":"25650 Hauterive La Fresse"},{"value":"VILLE_661992881","text":"25920 Mouthier Haute Pierre"},{"value":"VILLE_282615737","text":"26390 Hauterives"},{"value":"VILLE_725273969","text":"26620 Lus La Croix Haute"},{"value":"VILLE_678153120","text":"27120 Hardencourt Cocherel"},{"value":"VILLE_144611180","text":"27150 Hacqueville"},{"value":"VILLE_117827648","text":"27190 Ferrieres Haut Clocher"},{"value":"VILLE_912410809","text":"27190 Le Mesnil Hardray"},{"value":"VILLE_125165052","text":"27230 La Chapelle Hareng"},{"value":"VILLE_731652361","text":"27330 La Haye Saint Sylvestre"},{"value":"VILLE_758748978","text":"27350 Hauville"},{"value":"VILLE_672037184","text":"27350 La Haye Aubree"},{"value":"VILLE_741156616","text":"27350 La Haye De Routot"},{"value":"VILLE_131431174","text":"27370 La Harengere"},{"value":"VILLE_788150439","text":"27370 La Haye Du Theil"},{"value":"VILLE_849466666","text":"27370 Saint Amand Des Hautes Terres"},{"value":"VILLE_278916867","text":"27390 Notre Dame Du Hamel"},{"value":"VILLE_250905957","text":"27400 La Haye Le Comte"},{"value":"VILLE_83479231","text":"27400 La Haye Malherbe"},{"value":"VILLE_573769548","text":"27410 Saint Aubin Des Hayes"},{"value":"VILLE_448791847","text":"27630 Heubecourt Haricourt"},{"value":"VILLE_684475339","text":"27680 Trouville La Haule"},{"value":"VILLE_261434794","text":"27700 Harquency"},{"value":"VILLE_849768553","text":"27800 Harcourt"},{"value":"VILLE_451569342","text":"27800 La Haye De Calleville"},{"value":"VILLE_639100579","text":"28130 Hanches"},{"value":"VILLE_714525077","text":"28140 Bazoches Les Hautes"},{"value":"VILLE_450660936","text":"28170 Saint Maixme Hauterive"},{"value":"VILLE_691595720","text":"28410 Havelu"},{"value":"VILLE_557484391","text":"28410 Saint Lubin De La Haye"},{"value":"VILLE_669042882","text":"28480 Happonvilliers"},{"value":"VILLE_473133666","text":"29460 Hanvec"},{"value":"VILLE_577120725","text":"31540 Mourvilles Hautes"},{"value":"VILLE_194189219","text":"32110 Arblade Le Haut"},{"value":"VILLE_498912438","text":"32300 Lagarde Hachan"},{"value":"VILLE_549486632","text":"32550 Haulies"},{"value":"VILLE_337810706","text":"32730 Haget"},{"value":"VILLE_85559473","text":"33185 Le Haillan"},{"value":"VILLE_764440052","text":"33550 Haux"},{"value":"VILLE_907169980","text":"34610 Castanet Le Haut"},{"value":"VILLE_299261433","text":"38142 Clavans En Haut Oisans"},{"value":"VILLE_880087421","text":"38410 Vaulnaveys Le Haut"},{"value":"VILLE_423124286","text":"39120 Les Hays"},{"value":"VILLE_324526636","text":"39130 Hautecour"},{"value":"VILLE_480666311","text":"39460 Foncine Le Haut"},{"value":"VILLE_804324765","text":"40250 Hauriet"},{"value":"VILLE_445074103","text":"40280 Haut Mauco"},{"value":"VILLE_45580023","text":"40290 Habas"},{"value":"VILLE_215790640","text":"40300 Hastingues"},{"value":"VILLE_691604206","text":"40700 Hagetmau"},{"value":"VILLE_360746813","text":"41800 Les Hayes"},{"value":"VILLE_8572305","text":"42370 Saint Haon Le Chatel"},{"value":"VILLE_327444234","text":"42370 Saint Haon Le Vieux"},{"value":"VILLE_728006997","text":"42600 Magneux Haute Rive"},{"value":"VILLE_799436440","text":"42610 Saint Georges Haute Ville"},{"value":"VILLE_922243641","text":"43340 Saint Haon"},{"value":"VILLE_162252479","text":"44115 Haute Goulaine"},{"value":"VILLE_203612243","text":"44690 La Haie Fouassiere"},{"value":"VILLE_666987300","text":"46210 Labastide Du Haut Mont"},{"value":"VILLE_734467201","text":"47340 Hautefage La Tour"},{"value":"VILLE_728041948","text":"47380 Pinel Hauterive"},{"value":"VILLE_825910779","text":"47400 Hautesvignes"},{"value":"VILLE_991295597","text":"50120 Equeurdreville Hainneville"},{"value":"VILLE_373333792","text":"50250 La Haye Du Puits"},{"value":"VILLE_756242703","text":"50270 La Haye D'ectot"},{"value":"VILLE_204144705","text":"50300 Saint Jean De La Haize"},{"value":"VILLE_724686837","text":"50310 Le Ham"},{"value":"VILLE_849105304","text":"50320 La Haye Pesnel"},{"value":"VILLE_437672356","text":"50340 Siouville Hague"},{"value":"VILLE_850601026","text":"50390 Hautteville Bocage"},{"value":"VILLE_373118204","text":"50410 La Haye Bellefond"},{"value":"VILLE_707445380","text":"50440 Beaumont Hague"},{"value":"VILLE_798451631","text":"50440 Branville Hague"},{"value":"VILLE_868579179","text":"50440 Greville Hague"},{"value":"VILLE_908431099","text":"50440 Sainte Croix Hague"},{"value":"VILLE_581782167","text":"50450 Hambye"},{"value":"VILLE_733011968","text":"50490 La Ronde Haye"},{"value":"VILLE_53712569","text":"50570 Hauteville La Guichard"},{"value":"VILLE_932189651","text":"50590 Hauteville Sur Mer"},{"value":"VILLE_481873778","text":"50600 Saint Hilaire Du Harcouet"},{"value":"VILLE_318184780","text":"50690 Flottemanville Hague"},{"value":"VILLE_460393589","text":"50690 Hardinvast"},{"value":"VILLE_168708826","text":"50690 Teurtheville Hague"},{"value":"VILLE_794608544","text":"50730 Hamelin"},{"value":"VILLE_343180336","text":"51160 Hautvillers"},{"value":"VILLE_306710208","text":"51290 Hauteville"},{"value":"VILLE_877516312","text":"51290 Margerie Hancourt"},{"value":"VILLE_359273890","text":"51300 Haussignemont"},{"value":"VILLE_927931722","text":"51320 Haussimont"},{"value":"VILLE_745961160","text":"51800 Dommartin Sous Hans"},{"value":"VILLE_747096440","text":"51800 Hans"},{"value":"VILLE_939991734","text":"52100 Hallignicourt"},{"value":"VILLE_846879450","text":"52150 Hacourt"},{"value":"VILLE_312091582","text":"52150 Harreville Les Chanteurs"},{"value":"VILLE_290879690","text":"52160 Colmier Le Haut"},{"value":"VILLE_407055619","text":"52250 Verseilles Le Haut"},{"value":"VILLE_16475762","text":"52400 Coiffy Le Haut"},{"value":"VILLE_10820727","text":"52600 Haute Amance"},{"value":"VILLE_834050577","text":"53160 Hambers"},{"value":"VILLE_899708591","text":"53250 Le Ham"},{"value":"VILLE_596828464","text":"53300 La Haie Traversaine"},{"value":"VILLE_884501819","text":"53640 Hardanges"},{"value":"VILLE_126535267","text":"54110 Haraucourt"},{"value":"VILLE_366957270","text":"54120 Hablainville"},{"value":"VILLE_473721870","text":"54290 Haigneville"},{"value":"VILLE_802350122","text":"54290 Haussonville"},{"value":"VILLE_683360725","text":"54330 Hammeville"},{"value":"VILLE_771258148","text":"54380 Villers En Haye"},{"value":"VILLE_732042795","text":"54385 Domevre En Haye"},{"value":"VILLE_550237961","text":"54385 Rosieres En Haye"},{"value":"VILLE_84060727","text":"54450 Halloville"},{"value":"VILLE_967157991","text":"54450 Harbouey"},{"value":"VILLE_500162068","text":"54470 Fey En Haye"},{"value":"VILLE_8096817","text":"54470 Hageville"},{"value":"VILLE_909794448","text":"54470 Hamonville"},{"value":"VILLE_411696420","text":"54470 Vieville En Haye"},{"value":"VILLE_200668301","text":"54560 Mercy Le Haut"},{"value":"VILLE_828651927","text":"54620 Han Devant Pierrepont"},{"value":"VILLE_576080","text":"54740 Gerbecourt Et Haplemont"},{"value":"VILLE_864455960","text":"54740 Haroue"},{"value":"VILLE_195163638","text":"54760 Arraye Et Han"},{"value":"VILLE_893679422","text":"54800 Hannonville Suzemont"},{"value":"VILLE_547676169","text":"54800 Hatrize"},{"value":"VILLE_638362736","text":"54830 Haudonville"},{"value":"VILLE_983688752","text":"54840 Velaine En Haye"},{"value":"VILLE_320881895","text":"54860 Haucourt Moulaine"},{"value":"VILLE_645393676","text":"55000 Haironville"},{"value":"VILLE_323053057","text":"55000 Les Hauts De Chee"},{"value":"VILLE_347242407","text":"55100 Haudainville"},{"value":"VILLE_431686717","text":"55100 Haumont Pres Samogneux"},{"value":"VILLE_414246289","text":"55110 Vilosnes Haraumont"},{"value":"VILLE_387693864","text":"55130 Vaudeville Le Haut"},{"value":"VILLE_820810594","text":"55130 Vouthon Haut"},{"value":"VILLE_407253881","text":"55160 Harville"},{"value":"VILLE_705023263","text":"55160 Haudiomont"},{"value":"VILLE_473396087","text":"55210 Hannonville Sous Les Cotes"},{"value":"VILLE_902180006","text":"55210 Vigneulles Les Hattonchatel"},{"value":"VILLE_31195770","text":"55300 Han Sur Meuse"},{"value":"VILLE_206528669","text":"55400 Abaucourt Hautecourt"},{"value":"VILLE_214720339","text":"55600 Han Les Juvigny"},{"value":"VILLE_283487257","text":"55700 Halles Sous Les Cotes"},{"value":"VILLE_175973537","text":"57170 Hampont"},{"value":"VILLE_750014029","text":"57230 Hanviller"},{"value":"VILLE_403591420","text":"57230 Haspelschiedt"},{"value":"VILLE_12809701","text":"57260 Lindre Haute"},{"value":"VILLE_142143417","text":"57280 Hauconcourt"},{"value":"VILLE_428940618","text":"57300 Hagondange"},{"value":"VILLE_741098735","text":"57340 Haboudange"},{"value":"VILLE_355885038","text":"57340 Harprich"},{"value":"VILLE_555210853","text":"57370 Hangviller"},{"value":"VILLE_565581116","text":"57400 Haut Clocher"},{"value":"VILLE_339533419","text":"57430 Hazembourg"},{"value":"VILLE_190562305","text":"57470 Hombourg Haut"},{"value":"VILLE_253689981","text":"57480 Halstroff"},{"value":"VILLE_477292207","text":"57480 Haute Kontz"},{"value":"VILLE_358429931","text":"57530 Hayes"},{"value":"VILLE_849829155","text":"57550 Hargarten Aux Mines"},{"value":"VILLE_384920653","text":"57570 Hagen"},{"value":"VILLE_317269165","text":"57580 Han Sur Nied"},{"value":"VILLE_249888989","text":"57590 Hannocourt"},{"value":"VILLE_798903847","text":"57630 Haraucourt Sur Seille"},{"value":"VILLE_59208703","text":"57650 Havange"},{"value":"VILLE_237273269","text":"57690 Hallering"},{"value":"VILLE_771504747","text":"57690 Haute Vigneulles"},{"value":"VILLE_853803302","text":"57700 Hayange"},{"value":"VILLE_463731789","text":"57790 Hattigny"},{"value":"VILLE_436277594","text":"57850 Haselbourg"},{"value":"VILLE_34067689","text":"57870 Harreberg"},{"value":"VILLE_495370661","text":"57870 Hartzviller"},{"value":"VILLE_49389144","text":"57880 Ham Sous Varsberg"},{"value":"VILLE_273014950","text":"57910 Hambach"},{"value":"VILLE_264341419","text":"57970 Basse Ham"},{"value":"VILLE_788569351","text":"59121 Haulchin"},{"value":"VILLE_856355901","text":"59138 Hargnies"},{"value":"VILLE_826457906","text":"59151 Hamel"},{"value":"VILLE_619272216","text":"59178 Hasnon"},{"value":"VILLE_644919818","text":"59190 Hazebrouck"},{"value":"VILLE_964587081","text":"59191 Haucourt En Cambresis"},{"value":"VILLE_747576238","text":"59198 Haspres"},{"value":"VILLE_807969971","text":"59250 Halluin"},{"value":"VILLE_723665716","text":"59255 Haveluy"},{"value":"VILLE_283763912","text":"59268 Haynecourt"},{"value":"VILLE_157980461","text":"59294 Haussy"},{"value":"VILLE_780541683","text":"59320 Hallennes Lez Haubourdin"},{"value":"VILLE_382347325","text":"59320 Haubourdin"},{"value":"VILLE_193548669","text":"59330 Hautmont"},{"value":"VILLE_934674528","text":"59440 Haut Lieu"},{"value":"VILLE_139982450","text":"59494 Aubry Du Hainaut"},{"value":"VILLE_628363871","text":"59496 Hantay"},{"value":"VILLE_95832086","text":"59660 Haverskerque"},{"value":"VILLE_492310730","text":"59670 Hardifort"},{"value":"VILLE_984548198","text":"59870 Wandignies Hamage"},{"value":"VILLE_87932584","text":"60112 Haucourt"},{"value":"VILLE_198104449","text":"60120 Hardivillers"},{"value":"VILLE_833595459","text":"60210 Halloy"},{"value":"VILLE_542363940","text":"60210 Hautbos"},{"value":"VILLE_132053397","text":"60210 Le Hamel"},{"value":"VILLE_92812803","text":"60240 Hadancourt Le Haut Clocher"},{"value":"VILLE_41989399","text":"60240 Hardivillers En Vexin"},{"value":"VILLE_33670266","text":"60300 Aumont En Halatte"},{"value":"VILLE_147550008","text":"60350 Hautefontaine"},{"value":"VILLE_60797154","text":"60440 Nanteuil Le Haudouin"},{"value":"VILLE_862624006","text":"60490 Hainvillers"},{"value":"VILLE_280039387","text":"60510 Haudivillers"},{"value":"VILLE_752178077","text":"60540 Puiseux Le Hauberger"},{"value":"VILLE_45146965","text":"60550 Verneuil En Halatte"},{"value":"VILLE_750276667","text":"60650 Hannaches"},{"value":"VILLE_985111489","text":"60650 Hanvoile"},{"value":"VILLE_435792674","text":"60690 Haute Epine"},{"value":"VILLE_277479573","text":"61210 Habloville"},{"value":"VILLE_344547329","text":"61240 Champ Haut"},{"value":"VILLE_787995528","text":"61250 Hauterive"},{"value":"VILLE_683712424","text":"61250 Vingt Hanaps"},{"value":"VILLE_679721959","text":"61310 Le Pin Au Haras"},{"value":"VILLE_956929446","text":"61410 Haleine"},{"value":"VILLE_297173963","text":"61490 Saint Clair De Halouze"},{"value":"VILLE_922107042","text":"61700 La Haute Chapelle"},{"value":"VILLE_325517875","text":"62111 Hannescamps"},{"value":"VILLE_6021506","text":"62118 Hamblain Les Pres"},{"value":"VILLE_303591800","text":"62121 Hamelincourt"},{"value":"VILLE_199504861","text":"62123 Habarcq"},{"value":"VILLE_754743924","text":"62124 Haplincourt"},{"value":"VILLE_904022827","text":"62130 Hautecloque"},{"value":"VILLE_172847843","text":"62132 Hardinghen"},{"value":"VILLE_574306260","text":"62138 Haisnes"},{"value":"VILLE_134176006","text":"62144 Haute Avesnes"},{"value":"VILLE_490472854","text":"62147 Graincourt Les Havrincourt"},{"value":"VILLE_112082219","text":"62147 Havrincourt"},{"value":"VILLE_610272064","text":"62152 Neufchatel Hardelot"},{"value":"VILLE_416105786","text":"62156 Haucourt"},{"value":"VILLE_278096777","text":"62190 Ham En Artois"},{"value":"VILLE_831236927","text":"62270 Nuncq Hautecote"},{"value":"VILLE_895613042","text":"62340 Hames Boucres"},{"value":"VILLE_250351532","text":"62390 Haravesnes"},{"value":"VILLE_807500635","text":"62390 Quoeux Haut Mainil"},{"value":"VILLE_63391610","text":"62440 Harnes"},{"value":"VILLE_666984017","text":"62570 Hallines"},{"value":"VILLE_717575511","text":"62690 Izel Les Hameaux"},{"value":"VILLE_497183104","text":"62760 Halloy"},{"value":"VILLE_141191249","text":"62810 Hauteville"},{"value":"VILLE_162730161","text":"62830 Halinghen"},{"value":"VILLE_43768648","text":"62850 Haut Loquin"},{"value":"VILLE_136586424","text":"62940 Haillicourt"},{"value":"VILLE_886509343","text":"64240 Hasparren"},{"value":"VILLE_202030972","text":"64330 Mascaraas Haron"},{"value":"VILLE_470240702","text":"64370 Hagetaubin"},{"value":"VILLE_242217029","text":"64470 Haux"},{"value":"VILLE_606057840","text":"64470 Lacarry Arhan Charritte De Haut"},{"value":"VILLE_981969943","text":"64480 Halsou"},{"value":"VILLE_964030602","text":"64800 Haut De Bosdarros"},{"value":"VILLE_898246954","text":"65150 Hautaget"},{"value":"VILLE_155030248","text":"65200 Hauban"},{"value":"VILLE_927110332","text":"65230 Hachan"},{"value":"VILLE_628750363","text":"65700 Hagedet"},{"value":"VILLE_141204180","text":"67117 Handschuheim"},{"value":"VILLE_522737701","text":"67260 Harskirchen"},{"value":"VILLE_693369178","text":"67330 Hattmatt"},{"value":"VILLE_66919889","text":"67500 Haguenau"},{"value":"VILLE_832357967","text":"67690 Hatten"},{"value":"VILLE_135065310","text":"67700 Haegen"},{"value":"VILLE_605046662","text":"67980 Hangenbieten"},{"value":"VILLE_91595123","text":"68130 Hausgauen"},{"value":"VILLE_839601014","text":"68210 Hagenbach"},{"value":"VILLE_489540930","text":"68210 Traubach Le Haut"},{"value":"VILLE_348814035","text":"68220 Hagenthal Le Bas"},{"value":"VILLE_240315640","text":"68220 Hagenthal Le Haut"},{"value":"VILLE_917707511","text":"68220 Michelbach Le Haut"},{"value":"VILLE_881119147","text":"68220 Ranspach Le Haut"},{"value":"VILLE_305122347","text":"68290 Bourbach Le Haut"},{"value":"VILLE_594177108","text":"68360 Soultz Haut Rhin"},{"value":"VILLE_930666229","text":"68420 Hattstatt"},{"value":"VILLE_807314332","text":"68440 Habsheim"},{"value":"VILLE_952380862","text":"68440 Steinbrunn Le Haut"},{"value":"VILLE_406127138","text":"68500 Hartmannswiller"},{"value":"VILLE_864987400","text":"68510 Magstatt Le Haut"},{"value":"VILLE_283181823","text":"68520 Burnhaupt Le Haut"},{"value":"VILLE_660774165","text":"68580 Seppois Le Haut"},{"value":"VILLE_34260271","text":"68640 Muespach Le Haut"},{"value":"VILLE_723801677","text":"68700 Aspach Le Haut"},{"value":"VILLE_826589283","text":"68720 Spechbach Le Haut"},{"value":"VILLE_741984017","text":"68740 Rumersheim Le Haut"},{"value":"VILLE_23907035","text":"68780 Soppe Le Haut"},{"value":"VILLE_757047739","text":"69420 Les Haies"},{"value":"VILLE_41697637","text":"69610 Haute Rivoire"},{"value":"VILLE_120212855","text":"69610 Les Halles"},{"value":"VILLE_535151920","text":"69850 Saint Martin En Haut"},{"value":"VILLE_169807608","text":"70440 Haut Du Them Chateau Lambert"},{"value":"VILLE_614822626","text":"70800 Hautevelle"},{"value":"VILLE_389812793","text":"71600 Hautefond"},{"value":"VILLE_599851461","text":"72300 Auvers Le Hamon"},{"value":"VILLE_494959009","text":"73390 Hauteville"},{"value":"VILLE_208364105","text":"73600 Hautecour"},{"value":"VILLE_203232599","text":"73620 Hauteluce"},{"value":"VILLE_649937699","text":"74150 Hauteville Sur Fier"},{"value":"VILLE_442980123","text":"74420 Habere Lullin"},{"value":"VILLE_826619838","text":"74420 Habere Poche"},{"value":"VILLE_661647900","text":"76113 Hautot Sur Seine"},{"value":"VILLE_984203587","text":"76190 Hautot Le Vatois"},{"value":"VILLE_840383715","text":"76190 Hautot Saint Sulpice"},{"value":"VILLE_94857913","text":"76380 Val De La Haye"},{"value":"VILLE_468699750","text":"76390 Haudricourt"},{"value":"VILLE_542615624","text":"76440 Haucourt"},{"value":"VILLE_921905201","text":"76440 Haussez"},{"value":"VILLE_238163880","text":"76450 Hautot L'auvray"},{"value":"VILLE_372746380","text":"76450 Le Hanouard"},{"value":"VILLE_730559799","text":"76490 Saint Nicolas De La Haie"},{"value":"VILLE_330086687","text":"76550 Hautot Sur Mer"},{"value":"VILLE_194356924","text":"76560 Harcanville"},{"value":"VILLE_172073573","text":"76600 Le Havre"},{"value":"VILLE_468967056","text":"76610 Le Havre"},{"value":"VILLE_456996256","text":"76620 Le Havre"},{"value":"VILLE_102301820","text":"76640 Hattenville"},{"value":"VILLE_280826700","text":"76700 Harfleur"},{"value":"VILLE_843784579","text":"76780 La Hallotiere"},{"value":"VILLE_206680824","text":"76780 La Haye"},{"value":"VILLE_529051307","text":"76850 Beaumont Le Hareng"},{"value":"VILLE_796973420","text":"76850 Bosc Le Hard"},{"value":"VILLE_464622511","text":"77515 Hautefeuille"},{"value":"VILLE_157269641","text":"77580 La Haute Maison"},{"value":"VILLE_504916716","text":"78113 La Hauteville"},{"value":"VILLE_162118358","text":"78114 Magny Les Hameaux"},{"value":"VILLE_25005357","text":"78250 Hardricourt"},{"value":"VILLE_374708960","text":"78790 Hargeville"},{"value":"VILLE_319750056","text":"79110 Hanc"},{"value":"VILLE_273697728","text":"80110 Hangard"},{"value":"VILLE_654669231","text":"80131 Harbonnieres"},{"value":"VILLE_737306793","text":"80132 Hautvillers Ouville"},{"value":"VILLE_840441086","text":"80134 Hangest En Santerre"},{"value":"VILLE_21814845","text":"80200 Aizecourt Le Haut"},{"value":"VILLE_832588032","text":"80240 Hancourt"},{"value":"VILLE_474645567","text":"80250 Hallivillers"},{"value":"VILLE_910186766","text":"80300 Beaumont Hamel"},{"value":"VILLE_505886582","text":"80310 Hangest Sur Somme"},{"value":"VILLE_876299952","text":"80320 Hallu"},{"value":"VILLE_527082515","text":"80360 Hardecourt Aux Bois"},{"value":"VILLE_393834203","text":"80400 Esmery Hallon"},{"value":"VILLE_678482682","text":"80400 Ham"},{"value":"VILLE_738835055","text":"80440 Hailles"},{"value":"VILLE_864234696","text":"80490 Hallencourt"},{"value":"VILLE_903547078","text":"80500 Contoire Hamel"},{"value":"VILLE_217554894","text":"80500 Hargicourt"},{"value":"VILLE_589212104","text":"80560 Harponville"},{"value":"VILLE_7966973","text":"80600 Hem Hardinval"},{"value":"VILLE_333915928","text":"80670 Halloy Les Pernois"},{"value":"VILLE_79771075","text":"80670 Havernas"},{"value":"VILLE_466754386","text":"80690 Ailly Le Haut Clocher"},{"value":"VILLE_836235423","text":"80700 Hattencourt"},{"value":"VILLE_7563089","text":"80800 Hamelet"},{"value":"VILLE_667942155","text":"80800 Le Hamel"},{"value":"VILLE_934481973","text":"86310 Haims"},{"value":"VILLE_812510157","text":"88220 Hadol"},{"value":"VILLE_908861703","text":"88240 Harsault"},{"value":"VILLE_825602451","text":"88240 Hautmougey"},{"value":"VILLE_143061043","text":"88240 La Haye"},{"value":"VILLE_378944618","text":"88270 Hagecourt"},{"value":"VILLE_301528018","text":"88270 Harol"},{"value":"VILLE_663869327","text":"88300 Hagneville Et Roncourt"},{"value":"VILLE_142302473","text":"88300 Harchechamp"},{"value":"VILLE_186661200","text":"88300 Harmonville"},{"value":"VILLE_919704484","text":"88330 Hadigny Les Verrieres"},{"value":"VILLE_88029873","text":"88330 Haillainville"},{"value":"VILLE_855234923","text":"88500 Chef Haut"},{"value":"VILLE_124435235","text":"88700 Hardancourt"},{"value":"VILLE_501113449","text":"88800 Hareville"},{"value":"VILLE_396813910","text":"89160 Sennevoy Le Haut"},{"value":"VILLE_586989738","text":"89160 Villiers Les Hauts"},{"value":"VILLE_312470666","text":"89250 Hauterive"},{"value":"VILLE_2373412","text":"90200 Auxelles Haut"},{"value":"VILLE_567894078","text":"95640 Haravilliers"},{"value":"VILLE_213961807","text":"95780 Haute Isle"},{"value":"VILLE_964441480","text":"97119 Vieux Habitants"},{"value":"VILLE_918887023","text":"97137 Terre De Haut"},{"value":"VILLE_582692519","text":"97435 Saint Gilles Les Hauts"},{"value":"VILLE_217166394","text":"98734 Haamene"},{"value":"VILLE_995004763","text":"98767 Hao"}]